dyndebug/__init__.py
dyndebug-0.2.1.dist-info/METADATA
dyndebug-0.2.1.dist-info/WHEEL
dyndebug-0.2.1.dist-info/RECORD
