Metadata-Version: 2.1
Name: dyndebug
Version: 0.2.1
Summary: A library to dynamically enable debug through configuration
License: MIT
Author: aurecon
Requires-Python: >=3.8,<4.0
Classifier: License :: OSI Approved :: MIT License
Classifier: Programming Language :: Python :: 3
Classifier: Programming Language :: Python :: 3.8
Classifier: Programming Language :: Python :: 3.9
Classifier: Programming Language :: Python :: 3.10
Classifier: Programming Language :: Python :: 3.11
Requires-Dist: loguru (>=0.7.0,<0.8.0)
